{
  "Description": "UNIQUE -- No more than 1 enhancement of this type may be slotted by a character.  While slotted, it increases your Maximum Hit Points by 7.5%.",
  "SetName": "Attuned_Unbreakable_Guard_F",
  "FullName": "Boosts.Attuned_Unbreakable_Guard_F",
  "ImageName": "",
  "Power": [
    1119
  ],
  "SetType": 10,
  "DisplayName": "Attuned Unbreakable Guard F",
  "nArchetype": -1,
  "nID": 882,
  "SubName": "Set: Unbreakable Guard",
  "ATClass": "",
  "UIDTrunkSet": "",
  "nIDTrunkSet": -1,
  "UIDLinkSecondary": "",
  "nIDLinkSecondary": -1,
  "UIDMutexSets": [],
  "nIDMutexSets": [],
  "GroupName": "Boosts",
  "Powers": [
    {
      "PowerIndex": 1119,
      "PowerSetID": 882,
      "StaticIndex": 9289,
      "NGroupMembership": [],
      "FullName": "Boosts.Attuned_Unbreakable_Guard_F.Attuned_Unbreakable_Guard_F",
      "GroupName": "Boosts",
      "SetName": "Attuned_Unbreakable_Guard_F",
      "PowerName": "Attuned_Unbreakable_Guard_F",
      "DisplayName": "Unbreakable Guard: +7.5% Max HP",
      "Requires": {
        "ClassName": [],
        "ClassNameNot": [],
        "PowerID": [],
        "PowerIDNot": [],
        "NClassName": [],
        "NClassNameNot": [],
        "NPowerID": [],
        "NPowerIDNot": []
      },
      "PowerType": 3,
      "Accuracy": 1.0,
      "AccuracyMult": 1.0,
      "GroupMembership": [],
      "EntitiesAffected": 1,
      "EntitiesAutoHit": 1,
      "Target": 1,
      "TargetLoS": true,
      "ActivatePeriod": 10.0,
      "EffectArea": 1,
      "MaxBoosts": "6",
      "NumAllowed": 1,
      "BoostsAllowed": [
        "Magic_Boost",
        "Mutation_Boost",
        "Natural_Boost",
        "Res_Damage_Boost",
        "Science_Boost",
        "Technology_Boost"
      ],
      "Enhancements": [
        19
      ],
      "DescShort": "+7.5% Max HP",
      "DescLong": "UNIQUE -- No more than 1 enhancement of this type may be slotted by a character.  While slotted, it increases your Maximum Hit Points by 7.5%.",
      "SortOverride": true,
      "SetTypes": [],
      "Level": 1,
      "VariableName": "",
      "NIDSubPower": [],
      "UIDSubPower": [],
      "IgnoreEnh": [],
      "Ignore_Buff": [],
      "MutexAuto": true,
      "ForcedClass": "",
      "Effects": [
        {
          "MagnitudeExpression": "",
          "Probability": 1.0,
          "Mag": 0.075,
          "MagPercent": 7.50000048,
          "Duration": 10.25,
          "DisplayPercentage": true,
          "BaseProbability": 1.0,
          "Reward": "",
          "EffectId": "Ones",
          "Special": "",
          "EffectType": 28,
          "ETModifies": 77,
          "Summon": "",
          "nSummon": -1,
          "UIDClassName": "",
          "nIDClassName": -1,
          "ToWho": 2,
          "Scale": 0.075,
          "nMagnitude": 1.0,
          "nDuration": 10.25,
          "ModifierTable": "Melee_Ones",
          "nModifierTable": 41,
          "PowerFullName": "Boosts.Attuned_Unbreakable_Guard_F.Attuned_Unbreakable_Guard_F",
          "Absorbed_PowerType": 1,
          "Absorbed_Power_nID": -1,
          "Absorbed_Class_nID": -1,
          "Absorbed_EffectID": -1,
          "UniqueID": 1,
          "Override": "",
          "nOverride": -1
        }
      ],
      "BoostUsePlayerLevel": true,
      "FullSetName": "Boosts.Attuned_Unbreakable_Guard_F",
      "CastTime": 0.132,
      "AoEModifier": 1.0
    }
  ]
}