{
  "Description": "Enhances the taunt duration of a power by {Boost.Attrib.Taunt.Scale}% and reduces the recharge time of a power by {Boost.Attrib.Recharge.Scale}%.",
  "SetName": "Attuned_Mocking_Beratement_B",
  "FullName": "Boosts.Attuned_Mocking_Beratement_B",
  "ImageName": "",
  "Power": [
    804
  ],
  "SetType": 10,
  "DisplayName": "Attuned Mocking Beratement B",
  "nArchetype": -1,
  "nID": 567,
  "SubName": "Set: Mocking Beratement",
  "ATClass": "",
  "UIDTrunkSet": "",
  "nIDTrunkSet": -1,
  "UIDLinkSecondary": "",
  "nIDLinkSecondary": -1,
  "UIDMutexSets": [],
  "nIDMutexSets": [],
  "GroupName": "Boosts",
  "Powers": [
    {
      "PowerIndex": 804,
      "PowerSetID": 567,
      "StaticIndex": 6826,
      "NGroupMembership": [],
      "FullName": "Boosts.Attuned_Mocking_Beratement_B.Attuned_Mocking_Beratement_B",
      "GroupName": "Boosts",
      "SetName": "Attuned_Mocking_Beratement_B",
      "PowerName": "Attuned_Mocking_Beratement_B",
      "DisplayName": "Mocking Beratement: Taunt/Recharge",
      "Requires": {
        "ClassName": [],
        "ClassNameNot": [],
        "PowerID": [],
        "PowerIDNot": [],
        "NClassName": [],
        "NClassNameNot": [],
        "NPowerID": [],
        "NPowerIDNot": []
      },
      "PowerType": 3,
      "Accuracy": 1.0,
      "AccuracyMult": 1.0,
      "GroupMembership": [],
      "EntitiesAffected": 1,
      "EntitiesAutoHit": 1,
      "Target": 1,
      "TargetLoS": true,
      "ActivatePeriod": 10.0,
      "EffectArea": 1,
      "MaxBoosts": "6",
      "NumAllowed": 1,
      "BoostsAllowed": [
        "Magic_Boost",
        "Mutation_Boost",
        "Natural_Boost",
        "Science_Boost",
        "Taunt_Boost",
        "Technology_Boost"
      ],
      "Enhancements": [
        24
      ],
      "DescShort": "+Taunt, +Rech",
      "DescLong": "Enhances the taunt duration of a power by {Boost.Attrib.Taunt.Scale}% and reduces the recharge time of a power by {Boost.Attrib.Recharge.Scale}%.",
      "SortOverride": true,
      "SetTypes": [],
      "Level": 1,
      "VariableName": "",
      "NIDSubPower": [],
      "UIDSubPower": [],
      "IgnoreEnh": [],
      "Ignore_Buff": [],
      "MutexAuto": true,
      "ForcedClass": "",
      "Effects": [
        {
          "MagnitudeExpression": "",
          "Probability": 1.0,
          "Mag": 0.265,
          "MagPercent": 26.4999981,
          "Duration": 10.25,
          "DisplayPercentage": true,
          "BaseProbability": 1.0,
          "Reward": "",
          "EffectId": "Recharge",
          "Special": "",
          "EffectType": 9,
          "ETModifies": 25,
          "Summon": "",
          "nSummon": -1,
          "UIDClassName": "",
          "nIDClassName": -1,
          "ToWho": 2,
          "Scale": 0.625,
          "nMagnitude": 1.0,
          "nDuration": 10.25,
          "Aspect": 3,
          "ModifierTable": "Melee_Boosts_33",
          "nModifierTable": 78,
          "PowerFullName": "Boosts.Attuned_Mocking_Beratement_B.Attuned_Mocking_Beratement_B",
          "Absorbed_PowerType": 1,
          "Absorbed_Power_nID": -1,
          "Absorbed_Class_nID": -1,
          "Absorbed_EffectID": -1,
          "UniqueID": 1,
          "Override": "",
          "nOverride": -1
        },
        {
          "MagnitudeExpression": "",
          "Probability": 1.0,
          "Mag": 0.265,
          "MagPercent": 26.4999981,
          "Duration": 10.25,
          "DisplayPercentage": true,
          "BaseProbability": 1.0,
          "Reward": "",
          "EffectId": "Taunt",
          "Special": "",
          "nID": 1,
          "EffectType": 9,
          "MezType": 11,
          "ETModifies": 19,
          "Summon": "",
          "nSummon": -1,
          "UIDClassName": "",
          "nIDClassName": -1,
          "ToWho": 2,
          "Scale": 0.625,
          "nMagnitude": 1.0,
          "nDuration": 10.25,
          "Aspect": 3,
          "ModifierTable": "Melee_Boosts_33",
          "nModifierTable": 78,
          "PowerFullName": "Boosts.Attuned_Mocking_Beratement_B.Attuned_Mocking_Beratement_B",
          "Absorbed_PowerType": 1,
          "Absorbed_Power_nID": -1,
          "Absorbed_Class_nID": -1,
          "Absorbed_EffectID": -1,
          "UniqueID": 2,
          "Override": "",
          "nOverride": -1
        }
      ],
      "BoostUsePlayerLevel": true,
      "FullSetName": "Boosts.Attuned_Mocking_Beratement_B",
      "CastTime": 0.132,
      "AoEModifier": 1.0
    }
  ]
}