{
  "Description": "Ninjas",
  "SetName": "Genin",
  "FullName": "Mastermind_Pets.Genin",
  "ImageName": "",
  "Power": [
    5855,
    5856,
    5857,
    5858
  ],
  "SetType": 8,
  "DisplayName": "Genin",
  "nArchetype": -1,
  "nID": 2937,
  "SubName": "Ninjas",
  "ATClass": "",
  "UIDTrunkSet": "",
  "nIDTrunkSet": -1,
  "UIDLinkSecondary": "",
  "nIDLinkSecondary": -1,
  "UIDMutexSets": [],
  "nIDMutexSets": [],
  "GroupName": "Mastermind_Pets",
  "Powers": [
    {
      "PowerIndex": 5855,
      "PowerSetID": 2937,
      "StaticIndex": 1196,
      "NGroupMembership": [],
      "FullName": "Mastermind_Pets.Genin.Resistance",
      "GroupName": "Mastermind_Pets",
      "SetName": "Genin",
      "PowerName": "Resistance",
      "DisplayName": "Resistance",
      "Requires": {
        "ClassName": [],
        "ClassNameNot": [],
        "PowerID": [],
        "PowerIDNot": [],
        "NClassName": [],
        "NClassNameNot": [],
        "NPowerID": [],
        "NPowerIDNot": []
      },
      "PowerType": 1,
      "Accuracy": 1.0,
      "AccuracyMult": 1.0,
      "GroupMembership": [],
      "EntitiesAffected": 1,
      "EntitiesAutoHit": 1,
      "Target": 1,
      "TargetLoS": true,
      "ActivatePeriod": 10.0,
      "EffectArea": 1,
      "MaxBoosts": "",
      "NumAllowed": 1,
      "BoostsAllowed": [
        "SpeedRunning_Boost"
      ],
      "Enhancements": [
        20
      ],
      "IgnoreStrength": true,
      "DescShort": "Auto +DEF(Melee, Ranged, AoE), Res(Confuse, Taunt), +SPD,",
      "DescLong": "Genin have improved Defense to Melee, Ranged and AoE attacks. They are resistant to Confuse and Taunt and are excellent runners.  Genin have a Thunder Kick and Shurikens.",
      "SortOverride": true,
      "SetTypes": [],
      "Level": 1,
      "VariableName": "",
      "NIDSubPower": [],
      "UIDSubPower": [],
      "IgnoreEnh": [],
      "Ignore_Buff": [],
      "MutexAuto": true,
      "ForcedClass": "Class_Minion_Henchman",
      "Effects": [
        {
          "MagnitudeExpression": "",
          "Probability": 1.0,
          "Mag": 0.06972,
          "MagPercent": 6.972,
          "Duration": 10.25,
          "DisplayPercentage": true,
          "BaseProbability": 1.0,
          "Reward": "",
          "EffectId": "SpeedJumping",
          "Special": "",
          "EffectType": 5,
          "DamageType": 10,
          "Summon": "",
          "nSummon": -1,
          "Buffable": true,
          "UIDClassName": "",
          "nIDClassName": -1,
          "ToWho": 2,
          "Scale": 0.028,
          "nMagnitude": 1.0,
          "nDuration": 10.25,
          "Aspect": 4,
          "ModifierTable": "Melee_SpeedJumping",
          "nModifierTable": 48,
          "PowerFullName": "Mastermind_Pets.Genin.Resistance",
          "Absorbed_PowerType": 1,
          "Absorbed_Power_nID": -1,
          "Absorbed_Class_nID": -1,
          "Absorbed_EffectID": -1,
          "UniqueID": 1,
          "Override": "",
          "nOverride": -1
        },
        {
          "MagnitudeExpression": "",
          "Probability": 1.0,
          "Mag": 0.06972,
          "MagPercent": 6.972,
          "Duration": 10.25,
          "DisplayPercentage": true,
          "BaseProbability": 1.0,
          "Reward": "",
          "EffectId": "SpeedJumping",
          "Special": "",
          "nID": 1,
          "EffectType": 5,
          "DamageType": 11,
          "Summon": "",
          "nSummon": -1,
          "Buffable": true,
          "UIDClassName": "",
          "nIDClassName": -1,
          "ToWho": 2,
          "Scale": 0.028,
          "nMagnitude": 1.0,
          "nDuration": 10.25,
          "Aspect": 4,
          "ModifierTable": "Melee_SpeedJumping",
          "nModifierTable": 48,
          "PowerFullName": "Mastermind_Pets.Genin.Resistance",
          "Absorbed_PowerType": 1,
          "Absorbed_Power_nID": -1,
          "Absorbed_Class_nID": -1,
          "Absorbed_EffectID": -1,
          "UniqueID": 2,
          "Override": "",
          "nOverride": -1
        },
        {
          "MagnitudeExpression": "",
          "Probability": 1.0,
          "Mag": 0.06972,
          "MagPercent": 6.972,
          "Duration": 10.25,
          "DisplayPercentage": true,
          "BaseProbability": 1.0,
          "Reward": "",
          "EffectId": "SpeedJumping",
          "Special": "",
          "nID": 2,
          "EffectType": 5,
          "DamageType": 12,
          "Summon": "",
          "nSummon": -1,
          "Buffable": true,
          "UIDClassName": "",
          "nIDClassName": -1,
          "ToWho": 2,
          "Scale": 0.028,
          "nMagnitude": 1.0,
          "nDuration": 10.25,
          "Aspect": 4,
          "ModifierTable": "Melee_SpeedJumping",
          "nModifierTable": 48,
          "PowerFullName": "Mastermind_Pets.Genin.Resistance",
          "Absorbed_PowerType": 1,
          "Absorbed_Power_nID": -1,
          "Absorbed_Class_nID": -1,
          "Absorbed_EffectID": -1,
          "UniqueID": 3,
          "Override": "",
          "nOverride": -1
        },
        {
          "MagnitudeExpression": "",
          "Probability": 1.0,
          "Mag": 0.5,
          "MagPercent": 50.0,
          "Duration": 10.25,
          "DisplayPercentage": true,
          "BaseProbability": 1.0,
          "Reward": "",
          "EffectId": "Ones",
          "Special": "",
          "nID": 3,
          "EffectType": 20,
          "MezType": 1,
          "Summon": "",
          "nSummon": -1,
          "UIDClassName": "",
          "nIDClassName": -1,
          "ToWho": 2,
          "Scale": 0.5,
          "nMagnitude": 1.0,
          "nDuration": 10.25,
          "ModifierTable": "Melee_Ones",
          "nModifierTable": 41,
          "PowerFullName": "Mastermind_Pets.Genin.Resistance",
          "Absorbed_PowerType": 1,
          "Absorbed_Power_nID": -1,
          "Absorbed_Class_nID": -1,
          "Absorbed_EffectID": -1,
          "UniqueID": 4,
          "Override": "",
          "nOverride": -1
        },
        {
          "MagnitudeExpression": "",
          "Probability": 1.0,
          "Mag": -2.0,
          "MagPercent": -2.0,
          "Duration": 10.25,
          "BaseProbability": 1.0,
          "Reward": "",
          "EffectId": "Ones",
          "Special": "",
          "nID": 4,
          "EffectType": 19,
          "MezType": 1,
          "Summon": "",
          "nSummon": -1,
          "UIDClassName": "",
          "nIDClassName": -1,
          "ToWho": 2,
          "Scale": -2.0,
          "nMagnitude": 1.0,
          "nDuration": 10.25,
          "Aspect": 4,
          "ModifierTable": "Melee_Ones",
          "nModifierTable": 41,
          "PowerFullName": "Mastermind_Pets.Genin.Resistance",
          "Absorbed_PowerType": 1,
          "Absorbed_Power_nID": -1,
          "Absorbed_Class_nID": -1,
          "Absorbed_EffectID": -1,
          "UniqueID": 5,
          "Override": "",
          "nOverride": -1
        },
        {
          "MagnitudeExpression": "",
          "Probability": 1.0,
          "Mag": -2.0,
          "MagPercent": -2.0,
          "Duration": 10.25,
          "BaseProbability": 1.0,
          "Reward": "",
          "EffectId": "Ones",
          "Special": "",
          "nID": 5,
          "EffectType": 19,
          "MezType": 11,
          "Summon": "",
          "nSummon": -1,
          "UIDClassName": "",
          "nIDClassName": -1,
          "ToWho": 2,
          "Scale": -2.0,
          "nMagnitude": 1.0,
          "nDuration": 10.25,
          "Aspect": 4,
          "ModifierTable": "Melee_Ones",
          "nModifierTable": 41,
          "PowerFullName": "Mastermind_Pets.Genin.Resistance",
          "Absorbed_PowerType": 1,
          "Absorbed_Power_nID": -1,
          "Absorbed_Class_nID": -1,
          "Absorbed_EffectID": -1,
          "UniqueID": 6,
          "Override": "",
          "nOverride": -1
        },
        {
          "MagnitudeExpression": "",
          "Probability": 1.0,
          "Mag": 0.5,
          "MagPercent": 50.0,
          "Duration": 10.25,
          "DisplayPercentage": true,
          "BaseProbability": 1.0,
          "Reward": "",
          "EffectId": "Ones",
          "Special": "",
          "nID": 6,
          "EffectType": 32,
          "Summon": "",
          "nSummon": -1,
          "Buffable": true,
          "UIDClassName": "",
          "nIDClassName": -1,
          "ToWho": 2,
          "Scale": 0.5,
          "nMagnitude": 1.0,
          "nDuration": 10.25,
          "Aspect": 4,
          "ModifierTable": "Melee_Ones",
          "nModifierTable": 41,
          "PowerFullName": "Mastermind_Pets.Genin.Resistance",
          "Absorbed_PowerType": 1,
          "Absorbed_Power_nID": -1,
          "Absorbed_Class_nID": -1,
          "Absorbed_EffectID": -1,
          "UniqueID": 7,
          "Override": "",
          "nOverride": -1
        }
      ],
      "FullSetName": "Mastermind_Pets.Genin",
      "CastTime": 0.132,
      "AoEModifier": 1.0
    },
    {
      "CastTimeReal": 1.07,
      "ToggleCost": 5.2,
      "PowerIndex": 5856,
      "PowerSetID": 2937,
      "PowerSetIndex": 1,
      "StaticIndex": 1197,
      "NGroupMembership": [],
      "FullName": "Mastermind_Pets.Genin.Shuriken",
      "GroupName": "Mastermind_Pets",
      "SetName": "Genin",
      "PowerName": "Shuriken",
      "DisplayName": "Shuriken",
      "Requires": {
        "ClassName": [],
        "ClassNameNot": [],
        "PowerID": [],
        "PowerIDNot": [],
        "NClassName": [],
        "NClassNameNot": [],
        "NPowerID": [],
        "NPowerIDNot": []
      },
      "ModesDisallowed": 2,
      "Accuracy": 1.0,
      "AccuracyMult": 1.0,
      "AttackTypes": 18,
      "GroupMembership": [],
      "EntitiesAffected": 2048,
      "Target": 2048,
      "TargetLoS": true,
      "Range": 70.0,
      "EndCost": 5.2,
      "RechargeTime": 4.0,
      "EffectArea": 1,
      "MaxBoosts": "6",
      "NumAllowed": 1,
      "BoostsAllowed": [
        "Accuracy_Boost",
        "Damage_Boost",
        "EnduranceDiscount_Boost"
      ],
      "Enhancements": [
        1,
        4,
        8
      ],
      "DescShort": "Ranged, Minor DMG(Lethal)",
      "DescLong": "Small throwing weapon.",
      "SetTypes": [],
      "Level": 1,
      "VariableName": "",
      "NIDSubPower": [],
      "UIDSubPower": [],
      "IgnoreEnh": [
        14
      ],
      "Ignore_Buff": [],
      "MutexAuto": true,
      "ForcedClass": "Class_Minion_Henchman",
      "Effects": [
        {
          "MagnitudeExpression": "",
          "Probability": 1.0,
          "Mag": 19.4636,
          "MagPercent": 19.4636,
          "BaseProbability": 1.0,
          "Reward": "",
          "EffectId": "Damage",
          "Special": "",
          "EffectType": 3,
          "DamageType": 2,
          "Summon": "",
          "nSummon": -1,
          "Stacking": 1,
          "Buffable": true,
          "Resistible": true,
          "UIDClassName": "",
          "nIDClassName": -1,
          "ToWho": 1,
          "Scale": 1.0,
          "nMagnitude": 1.0,
          "Aspect": 2,
          "ModifierTable": "Ranged_Damage",
          "nModifierTable": 20,
          "PowerFullName": "Mastermind_Pets.Genin.Shuriken",
          "Absorbed_PowerType": 1,
          "Absorbed_Power_nID": -1,
          "Absorbed_Class_nID": -1,
          "Absorbed_EffectID": -1,
          "UniqueID": 1,
          "Override": "",
          "nOverride": -1
        },
        {
          "MagnitudeExpression": "",
          "Probability": 1.0,
          "Mag": 19.4636,
          "MagPercent": 19.4636,
          "InherentSpecial": true,
          "BaseProbability": 1.0,
          "Reward": "",
          "EffectId": "Damage",
          "Special": "",
          "nID": 1,
          "EffectType": 3,
          "DamageType": 2,
          "Summon": "",
          "nSummon": -1,
          "Stacking": 1,
          "Buffable": true,
          "Resistible": true,
          "SpecialCase": 9,
          "UIDClassName": "",
          "nIDClassName": -1,
          "ToWho": 1,
          "Scale": 1.0,
          "nMagnitude": 1.0,
          "Aspect": 2,
          "ModifierTable": "Ranged_Damage",
          "nModifierTable": 20,
          "PowerFullName": "Mastermind_Pets.Genin.Shuriken",
          "Absorbed_PowerType": 1,
          "Absorbed_Power_nID": -1,
          "Absorbed_Class_nID": -1,
          "Absorbed_EffectID": -1,
          "UniqueID": 2,
          "Override": "",
          "nOverride": -1
        }
      ],
      "FullSetName": "Mastermind_Pets.Genin",
      "CastTime": 1.31999993,
      "AoEModifier": 1.0
    },
    {
      "PowerIndex": 5857,
      "PowerSetID": 2937,
      "PowerSetIndex": 2,
      "StaticIndex": 1198,
      "NGroupMembership": [],
      "FullName": "Mastermind_Pets.Genin.Super_Leap",
      "GroupName": "Mastermind_Pets",
      "SetName": "Genin",
      "PowerName": "Super_Leap",
      "DisplayName": "Super Leap",
      "Requires": {
        "ClassName": [],
        "ClassNameNot": [],
        "PowerID": [],
        "PowerIDNot": [],
        "NClassName": [],
        "NClassNameNot": [],
        "NPowerID": [],
        "NPowerIDNot": []
      },
      "ModesDisallowed": 2,
      "PowerType": 1,
      "Accuracy": 1.0,
      "AccuracyMult": 1.0,
      "GroupMembership": [],
      "EntitiesAffected": 1,
      "EntitiesAutoHit": 1,
      "Target": 1,
      "TargetLoS": true,
      "RechargeTime": 10.0,
      "EffectArea": 1,
      "MaxBoosts": "",
      "NumAllowed": 1,
      "BoostsAllowed": [
        "Jump_Boost"
      ],
      "Enhancements": [
        15
      ],
      "DescShort": "+Jump",
      "DescLong": "Genin can jump high.",
      "SetTypes": [],
      "Level": 1,
      "VariableName": "",
      "NIDSubPower": [],
      "UIDSubPower": [],
      "IgnoreEnh": [],
      "Ignore_Buff": [],
      "MutexAuto": true,
      "ForcedClass": "Class_Minion_Henchman",
      "Effects": [
        {
          "MagnitudeExpression": "",
          "Probability": 1.0,
          "Mag": 27.8,
          "MagPercent": 2780.0,
          "Duration": 10.25,
          "DisplayPercentage": true,
          "BaseProbability": 1.0,
          "Reward": "",
          "EffectId": "Leap",
          "Special": "",
          "EffectType": 16,
          "Summon": "",
          "nSummon": -1,
          "Buffable": true,
          "UIDClassName": "",
          "nIDClassName": -1,
          "ToWho": 2,
          "Scale": 1.0,
          "nMagnitude": 1.0,
          "nDuration": 10.25,
          "Aspect": 4,
          "ModifierTable": "Melee_Leap",
          "nModifierTable": 44,
          "PowerFullName": "Mastermind_Pets.Genin.Super_Leap",
          "Absorbed_PowerType": 1,
          "Absorbed_Power_nID": -1,
          "Absorbed_Class_nID": -1,
          "Absorbed_EffectID": -1,
          "UniqueID": 1,
          "Override": "",
          "nOverride": -1
        },
        {
          "MagnitudeExpression": "",
          "Probability": 1.0,
          "Mag": 2.49,
          "MagPercent": 249.0,
          "Duration": 1.025,
          "DisplayPercentage": true,
          "BaseProbability": 1.0,
          "Reward": "",
          "EffectId": "SpeedJumping",
          "Special": "",
          "nID": 1,
          "EffectType": 17,
          "Summon": "",
          "nSummon": -1,
          "Buffable": true,
          "UIDClassName": "",
          "nIDClassName": -1,
          "ToWho": 2,
          "Scale": 1.0,
          "nMagnitude": 1.0,
          "nDuration": 1.025,
          "Aspect": 4,
          "ModifierTable": "Melee_SpeedJumping",
          "nModifierTable": 48,
          "PowerFullName": "Mastermind_Pets.Genin.Super_Leap",
          "Absorbed_PowerType": 1,
          "Absorbed_Power_nID": -1,
          "Absorbed_Class_nID": -1,
          "Absorbed_EffectID": -1,
          "UniqueID": 2,
          "Override": "",
          "nOverride": -1
        },
        {
          "MagnitudeExpression": "",
          "Probability": 1.0,
          "Mag": 0.35,
          "MagPercent": 35.0,
          "Duration": 10.25,
          "DisplayPercentage": true,
          "BaseProbability": 1.0,
          "Reward": "",
          "EffectId": "SpeedRunning",
          "Special": "",
          "nID": 2,
          "EffectType": 32,
          "Summon": "",
          "nSummon": -1,
          "Buffable": true,
          "UIDClassName": "",
          "nIDClassName": -1,
          "ToWho": 2,
          "Scale": 0.1,
          "nMagnitude": 1.0,
          "nDuration": 10.25,
          "Aspect": 4,
          "ModifierTable": "Melee_SpeedRunning",
          "nModifierTable": 45,
          "PowerFullName": "Mastermind_Pets.Genin.Super_Leap",
          "Absorbed_PowerType": 1,
          "Absorbed_Power_nID": -1,
          "Absorbed_Class_nID": -1,
          "Absorbed_EffectID": -1,
          "UniqueID": 3,
          "Override": "",
          "nOverride": -1
        },
        {
          "MagnitudeExpression": "",
          "Probability": 1.0,
          "Mag": 40.0,
          "MagPercent": 4000.0,
          "Duration": 10.25,
          "DisplayPercentage": true,
          "BaseProbability": 1.0,
          "Reward": "",
          "EffectId": "Control",
          "Special": "",
          "nID": 3,
          "EffectType": 21,
          "Summon": "",
          "nSummon": -1,
          "Buffable": true,
          "UIDClassName": "",
          "nIDClassName": -1,
          "ToWho": 2,
          "Scale": 10.0,
          "nMagnitude": 1.0,
          "nDuration": 10.25,
          "Aspect": 4,
          "ModifierTable": "Melee_Control",
          "nModifierTable": 49,
          "PowerFullName": "Mastermind_Pets.Genin.Super_Leap",
          "Absorbed_PowerType": 1,
          "Absorbed_Power_nID": -1,
          "Absorbed_Class_nID": -1,
          "Absorbed_EffectID": -1,
          "UniqueID": 4,
          "Override": "",
          "nOverride": -1
        },
        {
          "MagnitudeExpression": "",
          "Probability": 1.0,
          "Mag": 40.0,
          "MagPercent": 4000.0,
          "Duration": 10.25,
          "DisplayPercentage": true,
          "BaseProbability": 1.0,
          "Reward": "",
          "EffectId": "Friction",
          "Special": "",
          "nID": 4,
          "EffectType": 22,
          "Summon": "",
          "nSummon": -1,
          "Buffable": true,
          "UIDClassName": "",
          "nIDClassName": -1,
          "ToWho": 2,
          "Scale": 10.0,
          "nMagnitude": 1.0,
          "nDuration": 10.25,
          "Aspect": 4,
          "ModifierTable": "Melee_Friction",
          "nModifierTable": 50,
          "PowerFullName": "Mastermind_Pets.Genin.Super_Leap",
          "Absorbed_PowerType": 1,
          "Absorbed_Power_nID": -1,
          "Absorbed_Class_nID": -1,
          "Absorbed_EffectID": -1,
          "UniqueID": 5,
          "Override": "",
          "nOverride": -1
        }
      ],
      "FullSetName": "Mastermind_Pets.Genin",
      "CastTime": 0.132,
      "AoEModifier": 1.0
    },
    {
      "CastTimeReal": 1.07,
      "ToggleCost": 5.2,
      "PowerIndex": 5858,
      "PowerSetID": 2937,
      "PowerSetIndex": 3,
      "StaticIndex": 1199,
      "NGroupMembership": [],
      "FullName": "Mastermind_Pets.Genin.Thunder_Kick",
      "GroupName": "Mastermind_Pets",
      "SetName": "Genin",
      "PowerName": "Thunder_Kick",
      "DisplayName": "Thunder Kick",
      "Requires": {
        "ClassName": [],
        "ClassNameNot": [],
        "PowerID": [],
        "PowerIDNot": [],
        "NClassName": [],
        "NClassNameNot": [],
        "NPowerID": [],
        "NPowerIDNot": []
      },
      "ModesDisallowed": 2,
      "Accuracy": 1.0,
      "AccuracyMult": 1.0,
      "AttackTypes": 9,
      "GroupMembership": [],
      "EntitiesAffected": 2048,
      "Target": 2048,
      "TargetLoS": true,
      "Range": 7.0,
      "EndCost": 5.2,
      "RechargeTime": 3.0,
      "EffectArea": 1,
      "MaxBoosts": "6",
      "NumAllowed": 1,
      "BoostsAllowed": [
        "Accuracy_Boost",
        "Damage_Boost",
        "EnduranceDiscount_Boost",
        "Stunned_Boost"
      ],
      "Enhancements": [
        1,
        4,
        8,
        23
      ],
      "DescShort": "Disorient",
      "DescLong": "You have been Disoriented.",
      "SetTypes": [],
      "Level": 1,
      "VariableName": "",
      "NIDSubPower": [],
      "UIDSubPower": [],
      "IgnoreEnh": [
        13,
        14
      ],
      "Ignore_Buff": [],
      "MutexAuto": true,
      "ForcedClass": "Class_Minion_Henchman",
      "Effects": [
        {
          "MagnitudeExpression": "",
          "Probability": 1.0,
          "Mag": 25.0246,
          "MagPercent": 25.0246,
          "BaseProbability": 1.0,
          "Reward": "",
          "EffectId": "Damage",
          "Special": "",
          "EffectType": 3,
          "DamageType": 1,
          "Summon": "",
          "nSummon": -1,
          "Stacking": 1,
          "Buffable": true,
          "Resistible": true,
          "UIDClassName": "",
          "nIDClassName": -1,
          "ToWho": 1,
          "Scale": 1.0,
          "nMagnitude": 1.0,
          "Aspect": 2,
          "ModifierTable": "Melee_Damage",
          "PowerFullName": "Mastermind_Pets.Genin.Thunder_Kick",
          "Absorbed_PowerType": 1,
          "Absorbed_Power_nID": -1,
          "Absorbed_Class_nID": -1,
          "Absorbed_EffectID": -1,
          "UniqueID": 1,
          "Override": "",
          "nOverride": -1
        },
        {
          "MagnitudeExpression": "",
          "Probability": 0.1,
          "Mag": 2.0,
          "MagPercent": 2.0,
          "Duration": 6.705,
          "BaseProbability": 0.1,
          "Reward": "",
          "EffectId": "Stun",
          "Special": "",
          "nID": 1,
          "EffectType": 19,
          "MezType": 10,
          "Summon": "",
          "nSummon": -1,
          "Stacking": 1,
          "Buffable": true,
          "Resistible": true,
          "UIDClassName": "",
          "nIDClassName": -1,
          "PvMode": 1,
          "ToWho": 1,
          "Scale": 6.0,
          "nMagnitude": 2.0,
          "AttribType": 1,
          "Aspect": 4,
          "ModifierTable": "Melee_Stun",
          "nModifierTable": 5,
          "PowerFullName": "Mastermind_Pets.Genin.Thunder_Kick",
          "Absorbed_PowerType": 1,
          "Absorbed_Power_nID": -1,
          "Absorbed_Class_nID": -1,
          "Absorbed_EffectID": -1,
          "UniqueID": 2,
          "Override": "",
          "nOverride": -1
        },
        {
          "MagnitudeExpression": "",
          "Probability": 0.1,
          "Mag": 2.0,
          "MagPercent": 2.0,
          "Duration": 2.0,
          "BaseProbability": 0.1,
          "Reward": "",
          "EffectId": "Ones",
          "Special": "",
          "nID": 2,
          "EffectType": 19,
          "MezType": 10,
          "Summon": "",
          "nSummon": -1,
          "Stacking": 1,
          "Suppression": 31,
          "Buffable": true,
          "Resistible": true,
          "UIDClassName": "",
          "nIDClassName": -1,
          "PvMode": 2,
          "ToWho": 1,
          "Scale": 2.0,
          "nMagnitude": 2.0,
          "AttribType": 1,
          "Aspect": 4,
          "ModifierTable": "Melee_Ones",
          "nModifierTable": 41,
          "PowerFullName": "Mastermind_Pets.Genin.Thunder_Kick",
          "Absorbed_PowerType": 1,
          "Absorbed_Power_nID": -1,
          "Absorbed_Class_nID": -1,
          "Absorbed_EffectID": -1,
          "UniqueID": 3,
          "Override": "",
          "nOverride": -1
        },
        {
          "MagnitudeExpression": "",
          "Probability": 1.0,
          "Mag": 25.0246,
          "MagPercent": 25.0246,
          "InherentSpecial": true,
          "BaseProbability": 1.0,
          "Reward": "",
          "EffectId": "Damage",
          "Special": "",
          "nID": 3,
          "EffectType": 3,
          "DamageType": 1,
          "Summon": "",
          "nSummon": -1,
          "Stacking": 1,
          "Buffable": true,
          "Resistible": true,
          "SpecialCase": 9,
          "UIDClassName": "",
          "nIDClassName": -1,
          "ToWho": 1,
          "Scale": 1.0,
          "nMagnitude": 1.0,
          "Aspect": 2,
          "ModifierTable": "Melee_Damage",
          "PowerFullName": "Mastermind_Pets.Genin.Thunder_Kick",
          "Absorbed_PowerType": 1,
          "Absorbed_Power_nID": -1,
          "Absorbed_Class_nID": -1,
          "Absorbed_EffectID": -1,
          "UniqueID": 4,
          "Override": "",
          "nOverride": -1
        }
      ],
      "FullSetName": "Mastermind_Pets.Genin",
      "CastTime": 1.31999993,
      "AoEModifier": 1.0
    }
  ]
}