{
  "Description": "Vigilant Assault",
  "SetName": "Vigilant_Assault_Proc",
  "FullName": "Pets.Vigilant_Assault_Proc",
  "ImageName": "",
  "Power": [
    6714
  ],
  "SetType": 8,
  "DisplayName": "Vigilant Assault",
  "nArchetype": -1,
  "nID": 3257,
  "SubName": "Vigilant Assault",
  "ATClass": "",
  "UIDTrunkSet": "",
  "nIDTrunkSet": -1,
  "UIDLinkSecondary": "",
  "nIDLinkSecondary": -1,
  "UIDMutexSets": [],
  "nIDMutexSets": [],
  "GroupName": "Pets",
  "Powers": [
    {
      "PowerIndex": 6714,
      "PowerSetID": 3257,
      "StaticIndex": 8970,
      "NGroupMembership": [],
      "FullName": "Pets.Vigilant_Assault_Proc.Vigilant_Assault",
      "GroupName": "Pets",
      "SetName": "Vigilant_Assault_Proc",
      "PowerName": "Vigilant_Assault",
      "DisplayName": "Vigilant Assault",
      "Requires": {
        "ClassName": [],
        "ClassNameNot": [],
        "PowerID": [],
        "PowerIDNot": [],
        "NClassName": [],
        "NClassNameNot": [],
        "NPowerID": [],
        "NPowerIDNot": []
      },
      "PowerType": 1,
      "Accuracy": 1.0,
      "AccuracyMult": 1.0,
      "GroupMembership": [],
      "EntitiesAffected": 512,
      "EntitiesAutoHit": 512,
      "Target": 1,
      "TargetLoS": true,
      "ActivatePeriod": 9999.0,
      "EffectArea": 2,
      "Radius": 20.0,
      "MaxTargets": 16,
      "MaxBoosts": "6",
      "NumAllowed": 1,
      "BoostsAllowed": [],
      "Enhancements": [],
      "DescShort": "PBAoE +Absorb",
      "DescLong": "Vigilant Assault grants nearby allies a small amount of damage absorption.",
      "SortOverride": true,
      "SetTypes": [],
      "Level": 1,
      "VariableName": "",
      "NIDSubPower": [],
      "UIDSubPower": [],
      "IgnoreEnh": [],
      "Ignore_Buff": [],
      "MutexAuto": true,
      "ForcedClass": "Class_Minion_Pets",
      "Effects": [
        {
          "MagnitudeExpression": "",
          "Probability": 1.0,
          "Mag": 0.05,
          "MagPercent": 5.0,
          "DisplayPercentage": true,
          "BaseProbability": 1.0,
          "Reward": "",
          "EffectId": "Ones",
          "Special": "",
          "EffectType": 66,
          "Summon": "",
          "nSummon": -1,
          "UIDClassName": "",
          "nIDClassName": -1,
          "ToWho": 1,
          "Scale": 0.05,
          "nMagnitude": 1.0,
          "Aspect": 4,
          "ModifierTable": "Melee_Ones",
          "nModifierTable": 41,
          "PowerFullName": "Pets.Vigilant_Assault_Proc.Vigilant_Assault",
          "Absorbed_PowerType": 1,
          "Absorbed_Power_nID": -1,
          "Absorbed_Class_nID": -1,
          "Absorbed_EffectID": -1,
          "UniqueID": 1,
          "Override": "",
          "nOverride": -1
        },
        {
          "MagnitudeExpression": "Max.kHitPoints source> 0.05 *",
          "Probability": 1.0,
          "DisplayPercentage": true,
          "BaseProbability": 1.0,
          "Reward": "",
          "EffectId": "Ones",
          "Special": "",
          "nID": 1,
          "EffectType": 66,
          "Summon": "",
          "nSummon": -1,
          "UIDClassName": "",
          "nIDClassName": -1,
          "ToWho": 1,
          "Scale": 1.0,
          "nMagnitude": 1.0,
          "nDuration": 20.0,
          "AttribType": 2,
          "Aspect": 1,
          "ModifierTable": "Melee_Ones",
          "nModifierTable": 41,
          "PowerFullName": "Pets.Vigilant_Assault_Proc.Vigilant_Assault",
          "Absorbed_PowerType": 1,
          "Absorbed_Power_nID": -1,
          "Absorbed_Class_nID": -1,
          "Absorbed_EffectID": -1,
          "UniqueID": 2,
          "Override": "",
          "nOverride": -1
        }
      ],
      "FullSetName": "Pets.Vigilant_Assault_Proc",
      "CastTime": 0.132,
      "AoEModifier": 4.0
    }
  ]
}